aws_sns_slack_subscriber/__init__.py
aws_sns_slack_subscriber/slack_subscriber.py
aws_sns_slack_subscriber/src/__init__.py
aws_sns_slack_subscriber/src/index.py
aws_sns_slack_subscriber/src/colorizers/__init__.py
aws_sns_slack_subscriber/src/colorizers/base_colorizer.py
aws_sns_slack_subscriber/src/colorizers/error_colorizer.py
aws_sns_slack_subscriber/src/colorizers/success_colorizer.py
aws_sns_slack_subscriber/src/colorizers/warning_colorizer.py
aws_sns_slack_subscriber/src/handlers/__init__.py
aws_sns_slack_subscriber/src/handlers/base_event_handler.py
aws_sns_slack_subscriber/src/handlers/generic_event_handler.py
aws_sns_slack_subscriber/src/handlers/pipeline_event_handler.py
aws_sns_slack_subscriber-2.2.0.dist-info/LICENSE
aws_sns_slack_subscriber-2.2.0.dist-info/METADATA
aws_sns_slack_subscriber-2.2.0.dist-info/WHEEL
aws_sns_slack_subscriber-2.2.0.dist-info/top_level.txt
aws_sns_slack_subscriber-2.2.0.dist-info/RECORD
