Metadata-Version: 2.1
Name: aws-sns-slack-subscriber
Version: 2.2.0
Summary: AWS package which creates a Slack subscriber to a SNS Topic.
Home-page: https://github.com/idenfy/AwsSnsSlackSubscriber.git
Author: Laimonas Sutkus
Author-email: laimonas.sutkus@gmail.com (laimonas@idenfy.com)
License: GNU GENERAL PUBLIC LICENSE Version 3
Keywords: AWS SNS Topic Slack Lambda
Platform: UNKNOWN
Classifier: Programming Language :: Python :: 3
Classifier: Operating System :: OS Independent
Requires-Dist: aws-cdk.core (<2.0.0,>=1.60.0)
Requires-Dist: aws-cdk.aws-lambda (<2.0.0,>=1.60.0)
Requires-Dist: aws-cdk.aws-sns (<2.0.0,>=1.60.0)
Requires-Dist: aws-cdk.aws-sns-subscriptions (<2.0.0,>=1.60.0)
